{
  "size_x" : 2840,
  "size_y" : 1748,
  "Floors" : [
    {
      "x": 0,
      "y": 1392,
      "width": 2840,
      "height": 1402
    },
    {
      "x": 822,
      "y": 1360,
      "width": 930,
      "height": 1368
    },
    {
      "x": 930,
      "y": 1282,
      "width": 1037,
      "height": 1290
    },
    {
      "x": 1043,
      "y": 1206,
      "width": 1898,
      "height": 1216
    },
    {
      "x": 1903,
      "y": 1283,
      "width": 2009,
      "height": 1291
    },
    {
      "x": 2012,
      "y": 1359,
      "width": 2123,
      "height": 1367
    },
    {
      "x": 481,
      "y": 1055,
      "width": 756,
      "height": 1066
    },
    {
      "x": 823,
      "y": 1129,
      "width": 987,
      "height": 1139
    },
    {
      "x": 1960,
      "y": 1131,
      "width": 2124,
      "height": 1141
    },
    {
      "x": 2188,
      "y": 1056,
      "width": 2349,
      "height": 1065
    },
    {
      "x": 355,
      "y": 822,
      "width": 871,
      "height": 832
    },
    {
      "x": 820,
      "y": 748,
      "width": 986,
      "height": 758
    },
	    {
      "x": 1038,
      "y": 674,
      "width": 1899,
      "height": 684
    },
    {
      "x": 1954,
      "y": 597,
      "width": 2122,
      "height": 607
    },
    {
      "x": 2067,
      "y": 674,
      "width": 2242,
      "height": 684
    },
    {
      "x": 2180,
      "y": 750,
      "width": 2809,
      "height": 760
    },
    {
      "x": 22,
      "y": 446,
      "width": 539,
      "height": 456
    },
    {
      "x": 588,
      "y": 522,
      "width": 764,
      "height": 532
    },
    {
      "x": 814,
      "y": 597,
      "width": 990,
      "height": 607
    },
    {
      "x": 1043,
      "y": 295,
      "width": 1900,
      "height": 305
    },
    {
      "x": 2293,
      "y": 443,
      "width": 2810,
      "height": 453
    }
  ],
  "Slopes": [
    {
      "x": 675,
      "y": 993,
      "width": 690,
      "height": 1311
    },
    {
      "x": 777,
      "y": 759,
      "width": 815,
      "height": 1044
    },
    {
      "x": 2220,
      "y": 689,
      "width": 2260,
      "height": 969
    },
    {
      "x": 336,
      "y": 389,
      "width": 371,
      "height": 736
    },
    {
      "x": 1465,
      "y": 226,
      "width": 1500,
      "height": 625
    },
    {
      "x": 2536,
      "y": 382,
      "width": 2571,
      "height": 666
    }
  ],
  "BAML": [
    {
      "x": 0,
      "y": 1392,
      "width": 2840,
      "height": 1402,
      "limit" : 4
    },
    {
      "x": 1043,
      "y":  1206,
      "width":  1898,
      "height":  1216,
      "limit" : 2
    },
    {
      "x": 481,
      "y": 1055,
      "width": 756,
      "height": 1066,
      "limit" : 1
    },
    {
      "x": 355,
      "y": 822,
      "width": 871,
      "height": 832,
      "limit" : 1
    },
    {
      "x": 1038,
      "y": 674,
      "width": 1899,
      "height": 684,
      "limit" : 2
    },
    {
      "x": 2180,
      "y": 750,
      "width": 2809,
      "height": 760,
      "limit" : 2
    },
    {
      "x": 1043,
      "y": 295,
      "width": 1900,
      "height": 305,
      "limit" : 3
    }
  ]
}
